LICENCE
README.md
setup.py
src/cyg_mnt_point/__init__.py
src/cyg_mnt_point/mnt.py
src/cyg_mnt_point.egg-info/PKG-INFO
src/cyg_mnt_point.egg-info/SOURCES.txt
src/cyg_mnt_point.egg-info/dependency_links.txt
src/cyg_mnt_point.egg-info/top_level.txt