Metadata-Version: 2.1
Name: cyg-mnt-point
Version: 0.1
Summary: Search for the mount point in Cygwin by UUID disk partition
Home-page: https://github.com/Serhii5465/cyg_mnt_point
Author: Serhii5465
License: MIT
Platform: UNKNOWN
Classifier: Development Status :: 4 - Beta
Classifier: Environment :: Win32 (MS Windows)
Classifier: License :: OSI Approved :: MIT License
Classifier: Programming Language :: Python :: 3
Classifier: Operating System :: Microsoft :: Windows
Requires-Python: >=3.8
License-File: LICENCE
